pykit/__init__.py
pykit/alertlogger.py
pykit/autolog.py
pykit/inputs/__init__.py
pykit/inputs/loggableds.py
pykit/inputs/loggablepowerdistribution.py
pykit/inputs/loggablesystemstats.py
pykit/logdatareciever.py
pykit/loggedrobot.py
pykit/logger.py
pykit/logreplaysource.py
pykit/logtable.py
pykit/logvalue.py
pykit/networktables/__init__.py
pykit/networktables/loggeddashboardchooser.py
pykit/networktables/loggednetworkboolean.py
pykit/networktables/loggednetworkinput.py
pykit/networktables/loggednetworknumber.py
pykit/networktables/loggednetworkstring.py
pykit/networktables/loggednetworkvalue.py
pykit/networktables/nt4Publisher.py
pykit/wpilog/__init__.py
pykit/wpilog/wpilogconstants.py
pykit/wpilog/wpilogreader.py
pykit/wpilog/wpilogwriter.py
robotpy_pykit-1.0.3.dist-info/licenses/LICENSE
robotpy_pykit-1.0.3.dist-info/WHEEL
robotpy_pykit-1.0.3.dist-info/METADATA
robotpy_pykit-1.0.3.dist-info/RECORD
