Metadata-Version: 2.4
Name: robotpy-pykit
Version: 1.0.3
Summary: A logging, telemetry, and replay framework for FRC robots running python
Keywords: pykit,frc,robotics,logging,telemetry,replay
Author: Luke Maxwell
Author-email: Luke Maxwell <luke@whsrobotics.org>
License-Expression: BSD-3-Clause
License-File: LICENSE
Requires-Dist: pyntcore>=2026.1.1
Requires-Dist: robotpy-wpimath>=2026.1.1
Requires-Dist: robotpy-wpiutil>=2026.1.1
Requires-Dist: wpilib>=2026.1.1
Requires-Dist: robotpy-hal>=2026.1.1
Requires-Dist: pyfrc>=2026.0.1
Requires-Python: >=3.10
Project-URL: Homepage, https://github.com/1757WestwoodRobotics/PyKit
